README.rst
setup.py
datavis/__init__.py
datavis.egg-info/PKG-INFO
datavis.egg-info/SOURCES.txt
datavis.egg-info/dependency_links.txt
datavis.egg-info/requires.txt
datavis.egg-info/top_level.txt
datavis/models/__init__.py
datavis/models/_constants.py
datavis/models/_image_models.py
datavis/models/_params.py
datavis/models/_picking.py
datavis/models/_table_models.py
datavis/tests/__init__.py
datavis/tests/test_columnview.py
datavis/tests/test_commons.py
datavis/tests/test_dataview.py
datavis/tests/test_dualimagelistview.py
datavis/tests/test_filebrowser.py
datavis/tests/test_galleryview.py
datavis/tests/test_imagelistview.py
datavis/tests/test_imagemasklistview.py
datavis/tests/test_imagemaskvolumelistview.py
datavis/tests/test_imagemodels.py
datavis/tests/test_imageview.py
datavis/tests/test_itemsview.py
datavis/tests/test_mask_creator.py
datavis/tests/test_match_paths.py
datavis/tests/test_multislice_view.py
datavis/tests/test_paging.py
datavis/tests/test_params.py
datavis/tests/test_pickingview_cmp.py
datavis/tests/test_pickingview_mask.py
datavis/tests/test_pickingviewdefault.py
datavis/tests/test_pickingviewfilament.py
datavis/tests/test_roimasklistview.py
datavis/tests/test_roimaskvolumelistview.py
datavis/tests/test_slicesview.py
datavis/tests/test_spinslider.py
datavis/tests/test_textview.py
datavis/tests/test_toolbar.py
datavis/tests/test_volumelistview.py
datavis/tests/test_volumeview.py
datavis/utils/__init__.py
datavis/utils/path.py
datavis/utils/py23.py
datavis/views/__init__.py
datavis/views/_columns.py
datavis/views/_constants.py
datavis/views/_data_view.py
datavis/views/_gallery.py
datavis/views/_image_view.py
datavis/views/_items.py
datavis/views/_list_view.py
datavis/views/_multislice_view.py
datavis/views/_paging_view.py
datavis/views/_slices_view.py
datavis/views/_utils.py
datavis/views/_volume_view.py
datavis/views/model.py
datavis/views/picker_view.py
datavis/widgets/__init__.py
datavis/widgets/_axis.py
datavis/widgets/_common.py
datavis/widgets/_delegates.py
datavis/widgets/_dynamic.py
datavis/widgets/_paging.py
datavis/widgets/_panels.py
datavis/widgets/_plot.py
datavis/widgets/_spinbox.py
