Metadata-Version: 1.2
Name: datavis
Version: 0.0.4
Summary: Visualization tools for Scientific Data analysis (e.g Images and Tables)
Home-page: https://github.com/3dem/datavis
Author: J.M. De la Rosa Trevin,Pedro Hernandez Viga
Author-email: delarosatrevin@scilifelab.se, phviga2015@gmail.com
License: UNKNOWN
Project-URL: Bug Reports, https://github.com/3dem/datavis/issues
Project-URL: Source, https://github.com/3dem/datavis/
Platform: UNKNOWN
Classifier: Development Status :: 3 - Alpha
Classifier: License :: OSI Approved :: GNU General Public License v3 (GPLv3)
Classifier: Programming Language :: Python :: 3
